ciri/exception.py
ciri/abstract.py
ciri/validators.py
ciri/core.py
ciri/__init__.py
ciri/encoder.py
ciri/fields.py
ciri/compat.py
ciri/registry.py
ciri/ext/__init__.py
ciri/ext/sqlalchemy.py
ciri/util/__init__.py
ciri/util/dateparse.py
ciri-0.6.0.dist-info/WHEEL
ciri-0.6.0.dist-info/RECORD
ciri-0.6.0.dist-info/metadata.json
ciri-0.6.0.dist-info/top_level.txt
ciri-0.6.0.dist-info/METADATA
ciri-0.6.0.dist-info/DESCRIPTION.rst
