Metadata-Version: 2.0
Name: ciri
Version: 0.6.0
Summary: Python Schema Library
Home-page: https://github.com/ericb/ciri
Author: Eric Bobbitt
Author-email: eric@hellouser.net
License: MIT
Project-URL: Documentation, https://ciri.hellouser.net
Project-URL: Source, https://github.com/ericb/ciri
Project-URL: Tracker, https://github.com/ericb/ciri/issues
Keywords: schema serialization deserialization serialize deserialize encode decode validation validate rest api
Platform: UNKNOWN
Classifier: Development Status :: 3 - Alpha
Classifier: License :: OSI Approved :: MIT License
Classifier: Programming Language :: Python :: 2
Classifier: Programming Language :: Python :: 2.6
Classifier: Programming Language :: Python :: 2.7
Classifier: Programming Language :: Python :: 3
Classifier: Programming Language :: Python :: 3.4
Classifier: Programming Language :: Python :: 3.5
Classifier: Programming Language :: Python :: 3.6
Classifier: Topic :: Software Development :: Libraries
Classifier: Topic :: Utilities
Requires-Python: >=2.6
